{"areas":[{"councilName":"Centrum","relationId":11960504,"dedicatedCyclewaysLength":34228,"roadsLength":197784,"onRoadCycleLanesLength":11428,"sharedPathsLength":11233,"cyclewaysToRoadsRatio":0.17305747684342515,"safePathsToRoadsRatio":0.952240828378433,"councilArea":7237448.624902302,"underConstructionCyclewaysLength":50,"proposedCyclewaysLength":0,"safeStreetsLength":142877,"wikipedia":"nl:Amsterdam-Centrum","wikidata":"Q478282","wikidataPopulation":null,"safeRoadsToRoadsRatio":0.7223890709056344,"separatedCyclewayLengthPerResident":null,"separatedCyclewayMetresPerSquareKilometre":4257.213930348259,"wikidataId":"Q478282"},{"councilName":"Amsterdam","relationId":47811,"dedicatedCyclewaysLength":612702,"roadsLength":2605369,"onRoadCycleLanesLength":59889,"sharedPathsLength":270554,"cyclewaysToRoadsRatio":0.23516899141733857,"safePathsToRoadsRatio":0.9460928567124273,"councilArea":38119222.06856687,"underConstructionCyclewaysLength":10468,"proposedCyclewaysLength":793,"safeStreetsLength":1581665,"wikipedia":"nl:Amsterdam (gemeente)","wikidata":"Q9899","wikidataPopulation":917923,"safeRoadsToRoadsRatio":0.6070790740198413,"councilNameEnglish":"Amsterdam","separatedCyclewayLengthPerResident":0.6674873600508975,"separatedCyclewayMetresPerSquareKilometre":2796.8320628109736,"wikidataId":"Q9899"},{"councilName":"Paris","relationId":7444,"dedicatedCyclewaysLength":378311,"roadsLength":2025311,"onRoadCycleLanesLength":116402,"sharedPathsLength":59911,"cyclewaysToRoadsRatio":0.1867915594197632,"safePathsToRoadsRatio":0.8862357435475342,"councilArea":45777162.65190477,"underConstructionCyclewaysLength":1554,"proposedCyclewaysLength":0,"safeStreetsLength":1356681,"wikipedia":"fr:Paris","wikidata":"Q90","wikidataPopulation":2103778,"safeRoadsToRoadsRatio":0.6698630481935861,"separatedCyclewayLengthPerResident":0.17982458225154935,"separatedCyclewayMetresPerSquareKilometre":3589.288425047438,"wikidataId":"Q90"},{"councilName":"Paris 1er Arrondissement","relationId":20727,"dedicatedCyclewaysLength":7103,"roadsLength":66424,"onRoadCycleLanesLength":1834,"sharedPathsLength":4842,"cyclewaysToRoadsRatio":0.10693424063591472,"safePathsToRoadsRatio":0.6724677827291341,"councilArea":653040.572371332,"underConstructionCyclewaysLength":0,"proposedCyclewaysLength":0,"safeStreetsLength":32723,"wikipedia":"fr:1er arrondissement de Paris","wikidata":"Q161741","wikidataPopulation":15114,"safeRoadsToRoadsRatio":0.49263820305913525,"councilNameEnglish":"1st Arrondissement","separatedCyclewayLengthPerResident":0.46996162498345906,"separatedCyclewayMetresPerSquareKilometre":3881.4207650273224,"wikidataId":"Q161741"},{"councilName":"Københavns Kommune","relationId":2192363,"dedicatedCyclewaysLength":318758,"roadsLength":1429948,"onRoadCycleLanesLength":26279,"sharedPathsLength":79611,"cyclewaysToRoadsRatio":0.22291579833672273,"safePathsToRoadsRatio":0.4563683434642379,"councilArea":184928140.55494207,"underConstructionCyclewaysLength":0,"proposedCyclewaysLength":416,"safeStreetsLength":254214,"wikipedia":"da:Københavns Kommune","wikidata":"Q504125","wikidataPopulation":633021,"safeRoadsToRoadsRatio":0.17777849264448778,"councilNameEnglish":"Copenhagen Municipality","separatedCyclewayLengthPerResident":0.5035504351356432,"separatedCyclewayMetresPerSquareKilometre":3676.562860438293,"wikidataId":"Q504125"},{"councilName":"Frederiksberg Kommune","relationId":2186660,"dedicatedCyclewaysLength":36934,"roadsLength":145244,"onRoadCycleLanesLength":3185,"sharedPathsLength":6992,"cyclewaysToRoadsRatio":0.25428933381069097,"safePathsToRoadsRatio":0.441532868827628,"councilArea":10631553.154231165,"underConstructionCyclewaysLength":0,"proposedCyclewaysLength":0,"safeStreetsLength":20204,"wikipedia":"da:Frederiksberg Kommune","wikidata":"Q2488464","wikidataPopulation":104987,"safeRoadsToRoadsRatio":0.13910385282696702,"councilNameEnglish":"Frederiksberg Municipality","separatedCyclewayLengthPerResident":0.35179593663977443,"separatedCyclewayMetresPerSquareKilometre":4245.287356321839,"wikidataId":"Q2488464"},{"councilName":"Milano","relationId":44915,"dedicatedCyclewaysLength":160363,"roadsLength":2349015,"onRoadCycleLanesLength":43944,"sharedPathsLength":92161,"cyclewaysToRoadsRatio":0.06826818900688161,"safePathsToRoadsRatio":0.2743907552740191,"councilArea":558704970.0800774,"underConstructionCyclewaysLength":2086,"proposedCyclewaysLength":2052,"safeStreetsLength":392024,"wikipedia":"it:Milano","wikidata":"Q490","wikidataPopulation":1354196,"safeRoadsToRoadsRatio":0.1668886746146789,"councilNameEnglish":"Milan","separatedCyclewayLengthPerResident":0.11841934254716452,"separatedCyclewayMetresPerSquareKilometre":882.7159134694776,"wikidataId":"Q490"},{"councilName":"Australian Capital Territory","relationId":2354197,"dedicatedCyclewaysLength":47442,"roadsLength":4268844,"onRoadCycleLanesLength":529005,"sharedPathsLength":1012255,"cyclewaysToRoadsRatio":0.01111354736785884,"safePathsToRoadsRatio":0.25707685734123803,"councilArea":1663728488.1713212,"underConstructionCyclewaysLength":1675,"proposedCyclewaysLength":444,"safeStreetsLength":37724,"wikipedia":"en:Australian Capital Territory","wikidata":"Q3258","wikidataPopulation":481700,"safeRoadsToRoadsRatio":0.008837052841471836,"councilNameEnglish":"Australian Capital Territory","separatedCyclewayLengthPerResident":0.09848868590408968,"separatedCyclewayMetresPerSquareKilometre":20.119592875318066,"wikidataId":"Q3258"},{"councilName":"Bogotá","relationId":7426387,"dedicatedCyclewaysLength":265119,"roadsLength":7575792,"onRoadCycleLanesLength":47247,"sharedPathsLength":71726,"cyclewaysToRoadsRatio":0.03499554898022544,"safePathsToRoadsRatio":0.23203369363889612,"councilArea":979356143.6354207,"underConstructionCyclewaysLength":21971,"proposedCyclewaysLength":0,"safeStreetsLength":1420994,"wikidataPopulation":null,"safeRoadsToRoadsRatio":0.18757035568030378,"separatedCyclewayLengthPerResident":null,"separatedCyclewayMetresPerSquareKilometre":null},{"councilName":"Manhattan","relationId":8398124,"dedicatedCyclewaysLength":137712,"roadsLength":1215215,"onRoadCycleLanesLength":121285,"sharedPathsLength":45690,"cyclewaysToRoadsRatio":0.11332315680764309,"safePathsToRoadsRatio":0.15468291619178498,"councilArea":32615537.024330832,"underConstructionCyclewaysLength":2971,"proposedCyclewaysLength":1063,"safeStreetsLength":4571,"wikipedia":"en:Manhattan","wikidata":"Q11299","wikidataPopulation":1694251,"safeRoadsToRoadsRatio":0.003761474307015631,"councilNameEnglish":"Manhattan","separatedCyclewayLengthPerResident":0.08128193520322549,"separatedCyclewayMetresPerSquareKilometre":1582.896551724138,"wikidataId":"Q11299"},{"councilName":"Sydney","relationId":5750005,"dedicatedCyclewaysLength":170851,"roadsLength":23082255,"onRoadCycleLanesLength":471677,"sharedPathsLength":2069229,"cyclewaysToRoadsRatio":0.007401833139786386,"safePathsToRoadsRatio":0.10804823878776142,"councilArea":9839104172.741016,"underConstructionCyclewaysLength":17547,"proposedCyclewaysLength":28466,"safeStreetsLength":253917,"wikipedia":"en:Sydney","wikidata":"Q3130","wikidataPopulation":5450496,"safeRoadsToRoadsRatio":0.011000528327929832,"councilNameEnglish":"Sydney","separatedCyclewayLengthPerResident":0.03134595457000611,"separatedCyclewayMetresPerSquareKilometre":14.068063172109415,"wikidataId":"Q3130"},{"councilName":"Melbourne","relationId":4246124,"dedicatedCyclewaysLength":415988,"roadsLength":36706208,"onRoadCycleLanesLength":1672134,"sharedPathsLength":3356127,"cyclewaysToRoadsRatio":0.011332905867040256,"safePathsToRoadsRatio":0.10784369227134549,"councilArea":6698726032.295798,"underConstructionCyclewaysLength":57973,"proposedCyclewaysLength":19766,"safeStreetsLength":186418,"wikipedia":"en:Melbourne","wikidata":"Q3141","wikidataPopulation":5350705,"safeRoadsToRoadsRatio":0.005078650456075441,"councilNameEnglish":"Melbourne","separatedCyclewayLengthPerResident":0.07774452151632355,"separatedCyclewayMetresPerSquareKilometre":41.62793955769038,"wikidataId":"Q3141"}],"overpassQueryStrings":{"dedicatedCyclewaysQuery":"\n  [out:json];\nrel(999999);map_to_area->.region;\n(\n  way(area.region)[\"highway\"~\"cycleway\"][\"surface\"!~\"^(dirt|gravel|unpaved|ground|compacted|fine_gravel|shells|rock|pebblestone|earth|grass|sand)$\"][\"mtb\"!=\"yes\"][\"segregated\"!=\"no\"][\"foot\"!~\"designated|yes\"][\"access\"!~\"^(private|permissive|no)$\"];\n\n  way(area.region)[\"cycleway\"=\"track\"][\"segregated\"!=\"no\"][\"foot\"!~\"designated|yes\"][\"access\"!~\"^(private|permissive|no)$\"][\"surface\"!~\"^(dirt|gravel|unpaved|ground|compacted|fine_gravel|shells|rock|pebblestone|earth|grass|sand)$\"][\"mtb\"!=\"yes\"];\n  way(area.region)[\"cycleway:right\"=\"track\"][\"surface\"!~\"^(dirt|gravel|unpaved|ground|compacted|fine_gravel|shells|rock|pebblestone|earth|grass|sand)$\"][\"mtb\"!=\"yes\"];\n  way(area.region)[\"cycleway:left\"=\"track\"][\"surface\"!~\"^(dirt|gravel|unpaved|ground|compacted|fine_gravel|shells|rock|pebblestone|earth|grass|sand)$\"][\"mtb\"!=\"yes\"];\n  way(area.region)[\"cycleway:both\"=\"track\"][\"surface\"!~\"^(dirt|gravel|unpaved|ground|compacted|fine_gravel|shells|rock|pebblestone|earth|grass|sand)$\"][\"mtb\"!=\"yes\"];\n\n  // No longer includes painted lanes with painted buffer space (but no physical separator)\n  // Eg: 110kph Princes Motorway and only paint: https://www.openstreetmap.org/way/5067683\n\n  // Include painted lane ONLY if there is some sort of physical separator...\n  // These might include car parking/bollards/flex posts/bumps/planters etc\n  // See https://wiki.openstreetmap.org/wiki/Key:cycleway:separation\n  way(area.region)[\"cycleway\"=\"lane\"][\"cycleway:separation\"][\"cycleway:separation\"!~\"^(no|solid_line|dashed_line)$\"];\n  way(area.region)[\"cycleway:left\"=\"lane\"][\"cycleway:left:separation\"][\"cycleway:right:separation\"!~\"^(no|solid_line|dashed_line)$\"];\n  way(area.region)[\"cycleway:right\"=\"lane\"][\"cycleway:right:separation\"][\"cycleway:right:separation\"!~\"^(no|solid_line|dashed_line)$\"];\n  way(area.region)[\"cycleway:both\"=\"lane\"][\"cycleway:both:separation\"][\"cycleway:both:separation\"!~\"^(no|solid_line|dashed_line)$\"];\n\n  // ...or if there is an exclusive lane reserved for bicycles.\n  // As separation is commonly not tagged (eg. Paris), only include roads where vehicle speed <= 30kmh\n  // https://wiki.openstreetmap.org/wiki/Tag:cycleway:lane%3Dexclusive\n  way(area.region)[\"cycleway:left\"=\"lane\"][\"cycleway:left:lane\"=\"exclusive\"][\"maxspeed\"~\"^(5|10|15|20|25|30)$\"];\n  way(area.region)[\"cycleway:right\"=\"lane\"][\"cycleway:right:lane\"=\"exclusive\"][\"maxspeed\"~\"^(5|10|15|20|25|30)$\"];\n  way(area.region)[\"cycleway:both\"=\"lane\"][\"cycleway:both:lane\"=\"exclusive\"][\"maxspeed\"~\"^(5|10|15|20|25|30)$\"];\n  way(area.region)[\"cycleway\"=\"lane\"][\"cycleway:lane\"=\"exclusive\"][\"maxspeed\"~\"^(5|10|15|20|25|30)$\"];\n\n  // Include paved paths designated for bicycles\n  way(area.region)[\"highway=path\"][\"bicycle\"=\"designated\"][\"segregated\"!=\"no\"][\"access\"!~\"^(private|permissive|no)$\"][\"surface\"!~\"^(dirt|gravel|unpaved|ground|compacted|fine_gravel|shells|rock|pebblestone|earth|grass|sand)$\"][\"mtb\"!=\"yes\"];\n\n  // Include bicycle ramps\n  way(area.region)[\"access\"!~\"^(private|permissive|no)$\"][\"ramp:bicycle\"=\"yes\"];\n);\nout geom;\n","allCouncilsQuery":"\n[out:json][timeout:25];\nrel(999999);map_to_area->.searchArea;\n(\n  relation[\"admin_level\"=\"6\"][\"boundary_type\"!=\"unincorporated area\"](area.searchArea);\n);\nout tags;\n","onRoadCycleLanesQuery":"\n[out:json];\nrel(999999);map_to_area->.region;\n(\n  // Include on road painted lanes only if...\n  // ...there is not tag that they are not segregated from traffic...\n  way(area.region)[\"cycleway\"=\"lane\"][\"cycleway:separation\"!~\".*\"];\n  // ...if they are segrgated, it's only by a painted line\n  way(area.region)[\"cycleway\"=\"lane\"][\"cycleway:separation\"][\"cycleway:separation\"!~\"^(no|solid_line|dashed_line)$\"];\n\n  // Similar for left / right / both variants.\n\n  way(area.region)[\"cycleway:left\"=\"lane\"][\"cycleway:separation\"!~\".*\"];\n  way(area.region)[\"cycleway:left\"=\"lane\"][\"cycleway:left:separation\"][\"cycleway:left:separation\"!~\"^(no|solid_line|dashed_line)$\"];\n\n  way(area.region)[\"cycleway:right\"=\"lane\"][\"cycleway:separation\"!~\".*\"];\n  way(area.region)[\"cycleway:right\"=\"lane\"][\"cycleway:right:separation\"][\"cycleway:right:separation\"!~\"^(no|solid_line|dashed_line)$\"];\n\n  way(area.region)[\"cycleway:both\"=\"lane\"][\"cycleway:separation\"!~\".*\"];\n  way(area.region)[\"cycleway:both\"=\"lane\"][\"cycleway:both:separation\"][\"cycleway:both:separation\"!~\"^(no|solid_line|dashed_line)$\"];\n);\nout geom;\n","proposedCyclewaysQuery":"\n[out:json];\nrel(999999);map_to_area->.region;\n(\n  way(area.region)[\"highway\"=\"proposed\"][\"proposed\"=\"cycleway\"];\n  way(area.region)[\"proposed:highway\"=\"cycleway\"];\n);\nout geom;\n","relationInfoQuery":"\n[out:json][timeout:25];\nrelation(999999);\nout tags;\n","relationPointsQuery":"\n[out:json];\nrelation(999999);   // Replace RELATION_ID with the actual ID of the relation\nway(r);                 // Retrieves all ways in the relation\n(._;>;);                // Recursively retrieves all nodes in these ways\nout body;               // Outputs the result\n","roadsQuery":"\n[out:json];\nrel(999999);map_to_area->.region;\n(\n  way(area.region)[\"highway\"~\"^(motorway|trunk|primary|secondary|tertiary|unclassified|residential|living_street|service|pedestrian)$\"][\"access\"!~\"^(private|permissive|no)$\"][\"service\"!~\"^(driveway|parking_aisle)$\"];\n);\nout geom;\n","safeStreetsQuery":"\n  [out:json];\nrel(999999);map_to_area->.region;\n(\n  // Include all roads with a specified speed limit of <= 30kmh (except pedestrian streets that may disallow biycles by default)...\n  way(area.region)[\"access\"!~\"^(private|permissive|no)$\"][\"highway\"~\"^(motorway|trunk|primary|secondary|tertiary|unclassified|residential|living_street|service|pedestrian)$\"][\"access\"!~\"^(private|permissive|no)$\"][\"service\"!~\"^(driveway|parking_aisle)$\"][\"highway\"!=\"pedestrian\"][\"maxspeed\"~\"^(5|10|15|20|25|30)$\"]\n  // ...but exclude roads with an exclusive cycleway lane as this is counted as a dedicated cycleway.\n  [\"cycleway:left:lane\"!=\"exclusive\"]\n  [\"cycleway:right:lane\"!=\"exclusive\"]\n  [\"cycleway:lane\"!=\"exclusive\"]\n  [\"surface\"!~\"^(dirt|gravel|unpaved|ground|compacted|fine_gravel|shells|rock|pebblestone|earth|grass|sand)$\"][\"mtb\"!=\"yes\"];\n\n  // Include all roads with a specified advisory speed limit of <= 30kmh.\n  // Eg. Many streets are signposted 30kmh in Copenhagen.\n  // This doesn't pick up corner-speed advisory signs in Australia / EU as they are likely above\n  // 30kmh (and if not, are likely rejected by the bikes disallowed clause for motorway links)\n  way(area.region)\n  [\"highway\"~\"^(motorway|trunk|primary|secondary|tertiary|unclassified|residential|living_street|service|pedestrian)$\"][\"access\"!~\"^(private|permissive|no)$\"][\"service\"!~\"^(driveway|parking_aisle)$\"]\n  [\"access\"!~\"^(private|permissive|no)$\"]\n  [\"maxspeed:advisory\"~\"^(30|25|20|15|10)$\"]\n  [\"bicycle\"!~\"^(no|dismount)$\"];\n\n  // Include living/shared streets even if they don't have a speed limit, but not if they have a >=30 kmh speed limit\n  // (living streets imply bicycle=yes)\n  way(area.region)[\"highway\"=\"living_street\"][\"maxspeed\"!~\"^(40|50|60|70|80)$\"][\"access\"!~\"^(private|permissive|no)$\"][\"surface\"!~\"^(dirt|gravel|unpaved|ground|compacted|fine_gravel|shells|rock|pebblestone|earth|grass|sand)$\"][\"mtb\"!=\"yes\"];\n\n  // Include pedestrian streets tagged as explicitly allowing cycling as long as they have an\n  // advistory speed limit <= 30kmh (or no limit marked)\n  // Pedestrian streets don't imply bicycle=yes (and include George Street, Sydney)\n  way(area.region)[\"highway\"=\"pedestrian\"][\"bicycle\"=\"yes\"][\"maxspeed\"!~\"^(40|50|60|70|80)$\"][\"access\"!~\"^(private|permissive|no)$\"][\"surface\"!~\"^(dirt|gravel|unpaved|ground|compacted|fine_gravel|shells|rock|pebblestone|earth|grass|sand)$\"][\"mtb\"!=\"yes\"];\n  way(area.region)[\"highway\"=\"pedestrian\"][\"bicycle\"=\"yes\"][\"maxspeed:advisory\"~\"^(5|10|15|20|25|30)$\"][\"access\"!~\"^(private|permissive|no)$\"][\"surface\"!~\"^(dirt|gravel|unpaved|ground|compacted|fine_gravel|shells|rock|pebblestone|earth|grass|sand)$\"][\"mtb\"!=\"yes\"];\n\n);\nout geom;\n","sharedPathsQuery":"\n[out:json];\nrel(999999);map_to_area->.region;\n(\n  // Exclude footpath cycling for equal comparisons across states, though you could argue\n  // a legal cycling footpath is as valid as a shared path. I've added a note in the copy text that\n  // footpath cycling is excluded for clarity.\n\n  // Not all footpaths in legal juristictions are tagged with bicycle=yes as well so this would be\n  // incomplete without additional filters by legal juristiction.\n\n  // There may be false negatives here, but footpaths that allow cycling and aren't a shared path\n  // are somewhat rare (and are possibly tagging errors) in non-footpath cycling states.\n  // See overpass-turbo.eu/s/1FMP for these cases.\n\n  // Include shared paths\n  way(area.region)[\"highway\"=\"cycleway\"][\"segregated\"=\"no\"][\"access\"!~\"^(private|permissive|no)$\"][\"surface\"!~\"^(dirt|gravel|unpaved|ground|compacted|fine_gravel|shells|rock|pebblestone|earth|grass|sand)$\"][\"mtb\"!=\"yes\"];\n  way(area.region)[\"highway\"=\"cycleway\"][!\"segregated\"][\"foot\"~\"yes|designated\"][\"access\"!~\"^(private|permissive|no)$\"][\"surface\"!~\"^(dirt|gravel|unpaved|ground|compacted|fine_gravel|shells|rock|pebblestone|earth|grass|sand)$\"][\"mtb\"!=\"yes\"];\n\n  // Include paved paths as long as they aren't shared with pedestrians\n  way(area.region)[\"highway=path\"][\"bicycle\"=\"designated\"][\"segregated\"=\"yes\"][\"access\"!~\"^(private|permissive|no)$\"][\"surface\"!~\"^(dirt|gravel|unpaved|ground|compacted|fine_gravel|shells|rock|pebblestone|earth|grass|sand)$\"][\"mtb\"!=\"yes\"];\n\n  // Include pedestrian streets tagged as explicitly allowing cycling (eg. Martin Place, Sydney)\n  way(area.region)[\"highway\"=\"pedestrian\"][\"bicycle\"=\"yes\"][\"access\"!~\"^(private|permissive|no)$\"][\"surface\"!~\"^(dirt|gravel|unpaved|ground|compacted|fine_gravel|shells|rock|pebblestone|earth|grass|sand)$\"][\"mtb\"!=\"yes\"];\n\n  way(area.region)[\"cycleway\"=\"track\"][\"foot\"~\"designated|yes\"][\"access\"!~\"^(private|permissive|no)$\"][\"surface\"!~\"^(dirt|gravel|unpaved|ground|compacted|fine_gravel|shells|rock|pebblestone|earth|grass|sand)$\"][\"mtb\"!=\"yes\"];\n  way(area.region)[\"cycleway\"=\"track\"][\"highway\"=\"footway\"][\"access\"!~\"^(private|permissive|no)$\"][\"surface\"!~\"^(dirt|gravel|unpaved|ground|compacted|fine_gravel|shells|rock|pebblestone|earth|grass|sand)$\"][\"mtb\"!=\"yes\"];\n);\nout geom;\n","underConstructionCyclewaysQuery":"\n[out:json];\nrel(999999);map_to_area->.region;\n(\n  way(area.region)[\"highway\"=\"construction\"][\"construction\"=\"cycleway\"];\n  way(area.region)[\"construction:highway\"=\"cycleway\"];\n);\nout geom;\n","onewayRoadsQuery":"\n[out:json];\nrel(999999);map_to_area->.region;\n(\n  way(area.region)[\"highway\"~\"^(motorway|trunk|primary|secondary|tertiary|unclassified|residential|living_street|service|pedestrian)$\"][\"access\"!~\"^(private|permissive|no)$\"][\"service\"!~\"^(driveway|parking_aisle)$\"][\"oneway\"=\"yes\"];\n);\nout geom;\n","bidirectionalRoadsQuery":"\n[out:json];\nrel(999999);map_to_area->.region;\n(\n  way(area.region)[\"highway\"~\"^(motorway|trunk|primary|secondary|tertiary|unclassified|residential|living_street|service|pedestrian)$\"][\"access\"!~\"^(private|permissive|no)$\"][\"service\"!~\"^(driveway|parking_aisle)$\"][\"oneway\"!=\"yes\"];\n);\nout geom;\n","relationsInfoQuery":"[out:json];relation(999999);out tags;"}}